sphinx_jinja2_compat/__init__.py
sphinx_jinja2_compat/_installers.py
sphinx_jinja2_compat/_meta_path.py
sphinx_jinja2_compat-0.4.1.dist-info/LICENSE
sphinx_jinja2_compat-0.4.1.dist-info/METADATA
sphinx_jinja2_compat-0.4.1.dist-info/WHEEL
sphinx_jinja2_compat-0.4.1.dist-info/entry_points.txt
_sphinx_jinja2_compat.pth
sphinx_jinja2_compat-0.4.1.dist-info/RECORD
