Metadata-Version: 2.2
Name: sphinx-jinja2-compat
Version: 0.4.1
Summary: Patches Jinja2 v3 to restore compatibility with earlier Sphinx versions.
Author-email: Dominic Davis-Foster <dominic@davis-foster.co.uk>
License: MIT
Keywords: documentation,jinja2,sphinx
Home-page: https://github.com/sphinx-toolbox/sphinx-jinja2-compat
Project-URL: Issue Tracker, https://github.com/sphinx-toolbox/sphinx-jinja2-compat/issues
Project-URL: Source Code, https://github.com/sphinx-toolbox/sphinx-jinja2-compat
Platform: Windows
Platform: macOS
Platform: Linux
Classifier: Development Status :: 3 - Alpha
Classifier: Intended Audience :: Developers
Classifier: License :: OSI Approved :: MIT License
Classifier: Operating System :: OS Independent
Classifier: Programming Language :: Python
Classifier: Programming Language :: Python :: 3 :: Only
Classifier: Programming Language :: Python :: 3.7
Classifier: Programming Language :: Python :: 3.8
Classifier: Programming Language :: Python :: 3.9
Classifier: Programming Language :: Python :: 3.10
Classifier: Programming Language :: Python :: 3.11
Classifier: Programming Language :: Python :: 3.12
Classifier: Programming Language :: Python :: 3.13
Classifier: Programming Language :: Python :: Implementation :: CPython
Classifier: Programming Language :: Python :: Implementation :: PyPy
Classifier: Topic :: Documentation
Classifier: Topic :: Documentation :: Sphinx
Classifier: Topic :: Software Development :: Documentation
Requires-Python: >=3.6
Requires-Dist: jinja2>=2.10
Requires-Dist: markupsafe>=1
Requires-Dist: standard-imghdr==3.10.14; python_version >= "3.13"
